steamweb/__init__.py
steamweb/steamwebbrowser.py
steamweb/steamwebbrowsertk.py
steamweb-0.6.data/scripts/demo.py
steamweb-0.6.dist-info/DESCRIPTION.rst
steamweb-0.6.dist-info/METADATA
steamweb-0.6.dist-info/RECORD
steamweb-0.6.dist-info/WHEEL
steamweb-0.6.dist-info/metadata.json
steamweb-0.6.dist-info/top_level.txt
