Metadata-Version: 2.0
Name: steamweb
Version: 0.6
Summary: lib to access/use steam web pages (stuff not exposed via API)
Home-page: https://github.com/jayme-github/steamweb
Author: Jayme
Author-email: tuxnet@gmail.com
License: GNU Affero General Public License v3
Keywords: steam
Platform: any
Classifier: Development Status :: 4 - Beta
Classifier: Intended Audience :: Developers
Classifier: License :: OSI Approved :: GNU Affero General Public License v3
Classifier: Operating System :: OS Independent
Classifier: Programming Language :: Python
Requires-Dist: future (>=0.14.3)
Requires-Dist: pycrypto (>=2.6.1)
Requires-Dist: requests (>=2.7.0)
